stx_pysdk-1.0.19.dist-info/licenses/LICENSE
stxsdk/__init__.py
stxsdk/enums.py
stxsdk/exceptions.py
stxsdk/typings.py
stxsdk/utils.py
stxsdk/config/__init__.py
stxsdk/config/channels.py
stxsdk/config/configs.py
stxsdk/config/schema.graphql
stxsdk/services/__init__.py
stxsdk/services/authentication.py
stxsdk/services/base.py
stxsdk/services/channel.py
stxsdk/services/proxy.py
stxsdk/services/schema.py
stxsdk/services/selection.py
stxsdk/storage/__init__.py
stxsdk/storage/singleton.py
stxsdk/storage/user_storage.py
stx_pysdk-1.0.19.dist-info/METADATA
stx_pysdk-1.0.19.dist-info/WHEEL
stx_pysdk-1.0.19.dist-info/top_level.txt
stx_pysdk-1.0.19.dist-info/RECORD
