Metadata-Version: 2.4
Name: stx-pysdk
Version: 1.0.19
Summary: Sportsx Python SDK
Author-email: Sportsx <support@stxapp.io>
License:                                  Apache License
Classifier: Programming Language :: Python :: 3
Classifier: Programming Language :: Python :: 3.7
Classifier: Programming Language :: Python :: 3.8
Classifier: Programming Language :: Python :: 3.9
Classifier: Programming Language :: Python :: 3.10
Classifier: Programming Language :: Python :: 3.11
Classifier: Programming Language :: Python :: 3.12
Classifier: Programming Language :: Python :: 3.13
Classifier: License :: OSI Approved :: MIT License
Classifier: Operating System :: OS Independent
Requires-Python: >=3.7
License-File: LICENSE
Requires-Dist: websockets>=10.4
Requires-Dist: gql>=3.4.0
Requires-Dist: requests>=2.28.1
Requires-Dist: requests-toolbelt>=0.10.1
Dynamic: license-file
